css_parser/__init__.py
css_parser/_codec2.py
css_parser/_codec3.py
css_parser/_fetch.py
css_parser/_fetchgae.py
css_parser/codec.py
css_parser/cssproductions.py
css_parser/errorhandler.py
css_parser/helper.py
css_parser/parse.py
css_parser/prodparser.py
css_parser/profiles.py
css_parser/sac.py
css_parser/script.py
css_parser/serialize.py
css_parser/settings.py
css_parser/tokenize2.py
css_parser/util.py
css_parser/version.py
css_parser/css/__init__.py
css_parser/css/colors.py
css_parser/css/csscharsetrule.py
css_parser/css/csscomment.py
css_parser/css/cssfontfacerule.py
css_parser/css/cssimportrule.py
css_parser/css/cssmediarule.py
css_parser/css/cssnamespacerule.py
css_parser/css/csspagerule.py
css_parser/css/cssproperties.py
css_parser/css/cssrule.py
css_parser/css/cssrulelist.py
css_parser/css/cssstyledeclaration.py
css_parser/css/cssstylerule.py
css_parser/css/cssstylesheet.py
css_parser/css/cssunknownrule.py
css_parser/css/cssvalue.py
css_parser/css/cssvariablesdeclaration.py
css_parser/css/cssvariablesrule.py
css_parser/css/marginrule.py
css_parser/css/property.py
css_parser/css/selector.py
css_parser/css/selectorlist.py
css_parser/css/value.py
css_parser/encutils/__init__.py
css_parser/scripts/__init__.py
css_parser/scripts/csscapture.py
css_parser/scripts/csscombine.py
css_parser/scripts/cssparse.py
css_parser/stylesheets/__init__.py
css_parser/stylesheets/medialist.py
css_parser/stylesheets/mediaquery.py
css_parser/stylesheets/stylesheet.py
css_parser/stylesheets/stylesheetlist.py
css_parser-1.0.9.dist-info/COPYING
css_parser-1.0.9.dist-info/COPYING.LESSER
css_parser-1.0.9.dist-info/METADATA
css_parser-1.0.9.dist-info/WHEEL
css_parser-1.0.9.dist-info/top_level.txt
css_parser-1.0.9.dist-info/RECORD
