Metadata-Version: 2.1
Name: css-parser
Version: 1.0.9
Summary: A CSS Cascading Style Sheets library for Python
Home-page: https://github.com/ebook-utils/css-parser
Author: Various People
Author-email: redacted@anonymous.net
License: LGPL 3.0 or later
Keywords: CSS,Cascading Style Sheets,CSSParser,DOM Level 2 Stylesheets,DOM Level 2 CSS
Classifier: Development Status :: 5 - Production/Stable
Classifier: Environment :: Web Environment
Classifier: Intended Audience :: Developers
Classifier: License :: OSI Approved :: GNU Library or Lesser General Public License (LGPL)
Classifier: Operating System :: OS Independent
Classifier: Programming Language :: Python
Classifier: Programming Language :: Python :: 2
Classifier: Programming Language :: Python :: 3
Classifier: Topic :: Internet
Classifier: Topic :: Software Development :: Libraries :: Python Modules
Classifier: Topic :: Text Processing :: Markup :: HTML
License-File: COPYING
License-File: COPYING.LESSER
